CHANGES.rst
CONTRIBUTORS.rst
MANIFEST.in
README.rst
setup.py
docs/LICENSE.GPL
docs/LICENSE.rst
docs/index.rst
src/visaplan/__init__.py
src/visaplan.recipe.symlinks.egg-info/PKG-INFO
src/visaplan.recipe.symlinks.egg-info/SOURCES.txt
src/visaplan.recipe.symlinks.egg-info/dependency_links.txt
src/visaplan.recipe.symlinks.egg-info/entry_points.txt
src/visaplan.recipe.symlinks.egg-info/namespace_packages.txt
src/visaplan.recipe.symlinks.egg-info/not-zip-safe
src/visaplan.recipe.symlinks.egg-info/requires.txt
src/visaplan.recipe.symlinks.egg-info/top_level.txt
src/visaplan/recipe/__init__.py
src/visaplan/recipe/symlinks/.__init__.py.swp
src/visaplan/recipe/symlinks/.utils.py.swp
src/visaplan/recipe/symlinks/__init__.py
src/visaplan/recipe/symlinks/__init__.py~
src/visaplan/recipe/symlinks/utils.py
src/visaplan/recipe/symlinks/utils.py~
src/visaplan/recipe/tests/test_doctests.py