Metadata-Version: 2.1
Name: visaplan.recipe.symlinks
Version: 0.1.dev1
Summary: Create resource symlinks for Zope instances
Home-page: https://pypi.org/project/visaplan.recipe.symlinks
Author: Tobias Herp
Author-email: tobias.herp@visaplan.com
License: GPL version 2
Platform: UNKNOWN
Classifier: Framework :: Buildout
Classifier: Framework :: Zope
Classifier: Programming Language :: Python
Classifier: Programming Language :: Python :: 2.7
Classifier: Intended Audience :: Developers
Classifier: Intended Audience :: System Administrators
Classifier: Operating System :: POSIX
Classifier: License :: OSI Approved :: GNU General Public License v2 (GPLv2)
Provides-Extra: test
